atlas_orchestrator/__init__.py
atlas_orchestrator/analytics.py
atlas_orchestrator/bootstrap.py
atlas_orchestrator/cli.py
atlas_orchestrator/config.py
atlas_orchestrator/container.py
atlas_orchestrator/logging.py
atlas_orchestrator/plugins.py
atlas_orchestrator/sdk.py
atlas_orchestrator/workflows.py
atlas_orchestrator/ai/__init__.py
atlas_orchestrator/ai/anthropic.py
atlas_orchestrator/ai/azure.py
atlas_orchestrator/ai/base.py
atlas_orchestrator/ai/exceptions.py
atlas_orchestrator/ai/factory.py
atlas_orchestrator/ai/fallback.py
atlas_orchestrator/ai/openrouter.py
atlas_orchestrator/ai/usage.py
atlas_orchestrator/context/__init__.py
atlas_orchestrator/context/builder.py
atlas_orchestrator/context/cache.py
atlas_orchestrator/context/models.py
atlas_orchestrator/drafting/__init__.py
atlas_orchestrator/drafting/generator.py
atlas_orchestrator/drafting/models.py
atlas_orchestrator/drafting/repository.py
atlas_orchestrator/drafting/service.py
atlas_orchestrator/drafting/tools.py
atlas_orchestrator/planning/__init__.py
atlas_orchestrator/planning/models.py
atlas_orchestrator/planning/repository.py
atlas_orchestrator/planning/service.py
atlas_orchestrator/premium_api/__init__.py
atlas_orchestrator/premium_api/api.py
atlas_orchestrator/premium_api/audit.py
atlas_orchestrator/premium_api/auth.py
atlas_orchestrator/premium_api/billing.py
atlas_orchestrator/premium_api/bootstrap.py
atlas_orchestrator/premium_api/client.py
atlas_orchestrator/premium_api/config.py
atlas_orchestrator/premium_api/hashing.py
atlas_orchestrator/premium_api/jobs.py
atlas_orchestrator/premium_api/models.py
atlas_orchestrator/premium_api/observability.py
atlas_orchestrator/premium_api/providers.py
atlas_orchestrator/premium_api/queue.py
atlas_orchestrator/premium_api/rate_limiter.py
atlas_orchestrator/premium_api/secrets.py
atlas_orchestrator/premium_api/security.py
atlas_orchestrator/premium_api/server.py
atlas_orchestrator/premium_api/services.py
atlas_orchestrator/premium_api/storage.py
atlas_orchestrator-0.2.1.dist-info/METADATA
atlas_orchestrator-0.2.1.dist-info/WHEEL
atlas_orchestrator-0.2.1.dist-info/entry_points.txt
atlas_orchestrator-0.2.1.dist-info/top_level.txt
atlas_orchestrator-0.2.1.dist-info/RECORD
