Metadata-Version: 2.4
Name: atlas-orchestrator
Version: 0.2.1
Summary: Foundational scaffolding for the Atlas Orchestrator workflow platform
Author: Atlas Orchestrator Team
Requires-Python: >=3.10
Requires-Dist: pydantic>=2.5
Requires-Dist: pyyaml>=6.0
Requires-Dist: typer>=0.9
Requires-Dist: rich>=13.7
Requires-Dist: fastapi>=0.111
Requires-Dist: uvicorn>=0.30
Requires-Dist: argon2-cffi>=23.1
Requires-Dist: redis>=5.0
Requires-Dist: httpx>=0.27
Provides-Extra: dev
Requires-Dist: pytest>=7.4; extra == "dev"
Requires-Dist: pytest-cov>=4.1; extra == "dev"
Requires-Dist: mypy>=1.8; extra == "dev"
Requires-Dist: ruff>=0.4; extra == "dev"
